requirements.txt
setup.py
octicons16px/__init__.py
octicons16px/alert.py
octicons16px/archive.py
octicons16px/arrow_both.py
octicons16px/arrow_down.py
octicons16px/arrow_left.py
octicons16px/arrow_right.py
octicons16px/arrow_up.py
octicons16px/beaker.py
octicons16px/bell.py
octicons16px/bell_slash.py
octicons16px/bold.py
octicons16px/book.py
octicons16px/bookmark.py
octicons16px/bookmark_slash.py
octicons16px/briefcase.py
octicons16px/broadcast.py
octicons16px/browser.py
octicons16px/bug.py
octicons16px/calendar.py
octicons16px/check.py
octicons16px/check_circle.py
octicons16px/check_circle_fill.py
octicons16px/checklist.py
octicons16px/chevron_down.py
octicons16px/chevron_left.py
octicons16px/chevron_right.py
octicons16px/chevron_up.py
octicons16px/circle_slash.py
octicons16px/clippy.py
octicons16px/clock.py
octicons16px/code.py
octicons16px/code_review.py
octicons16px/code_square.py
octicons16px/comment.py
octicons16px/comment_discussion.py
octicons16px/cpu.py
octicons16px/credit_card.py
octicons16px/cross_reference.py
octicons16px/dash.py
octicons16px/database.py
octicons16px/desktop_download.py
octicons16px/device_camera.py
octicons16px/device_camera_video.py
octicons16px/device_desktop.py
octicons16px/device_mobile.py
octicons16px/diff.py
octicons16px/diff_added.py
octicons16px/diff_ignored.py
octicons16px/diff_modified.py
octicons16px/diff_removed.py
octicons16px/diff_renamed.py
octicons16px/dot.py
octicons16px/dot_fill.py
octicons16px/download.py
octicons16px/ellipsis.py
octicons16px/eye.py
octicons16px/eye_closed.py
octicons16px/file.py
octicons16px/file_binary.py
octicons16px/file_code.py
octicons16px/file_diff.py
octicons16px/file_directory.py
octicons16px/file_submodule.py
octicons16px/file_symlink_file.py
octicons16px/file_zip.py
octicons16px/filter.py
octicons16px/flame.py
octicons16px/fold.py
octicons16px/fold_down.py
octicons16px/fold_up.py
octicons16px/gear.py
octicons16px/gift.py
octicons16px/git_branch.py
octicons16px/git_commit.py
octicons16px.egg-info/PKG-INFO
octicons16px.egg-info/SOURCES.txt
octicons16px.egg-info/dependency_links.txt
octicons16px.egg-info/top_level.txt