Metadata-Version: 2.1
Name: octicons16px
Version: 2020.10.22
Summary: github octicons 16px
Home-page: https://github.com/andrewp-as-is/octicons16px.py
License: Unlicense
Keywords: octicons
Platform: UNKNOWN
Classifier: License :: Public Domain
Classifier: Operating System :: OS Independent
Classifier: Programming Language :: Python :: 3
